odoo/addons/ssi_infrastructure_server/README.rst
odoo/addons/ssi_infrastructure_server/__init__.py
odoo/addons/ssi_infrastructure_server/__manifest__.py
odoo/addons/ssi_infrastructure_server/data/approval_template_data.xml
odoo/addons/ssi_infrastructure_server/data/ir_sequence_data.xml
odoo/addons/ssi_infrastructure_server/data/policy_template_data.xml
odoo/addons/ssi_infrastructure_server/data/sequence_template_data.xml
odoo/addons/ssi_infrastructure_server/models/__init__.py
odoo/addons/ssi_infrastructure_server/models/server.py
odoo/addons/ssi_infrastructure_server/models/server_type.py
odoo/addons/ssi_infrastructure_server/security/ir.model.access.csv
odoo/addons/ssi_infrastructure_server/security/ir_module_category_data.xml
odoo/addons/ssi_infrastructure_server/security/ir_rule_data.xml
odoo/addons/ssi_infrastructure_server/security/res_group_data.xml
odoo/addons/ssi_infrastructure_server/static/description/icon.png
odoo/addons/ssi_infrastructure_server/views/server_type_views.xml
odoo/addons/ssi_infrastructure_server/views/server_views.xml
odoo14_addon_ssi_infrastructure_server-14.0.2.2.0.dist-info/METADATA
odoo14_addon_ssi_infrastructure_server-14.0.2.2.0.dist-info/WHEEL
odoo14_addon_ssi_infrastructure_server-14.0.2.2.0.dist-info/top_level.txt
odoo14_addon_ssi_infrastructure_server-14.0.2.2.0.dist-info/RECORD
